[
    {
        "case_id": "sample",
        "startTime": "YYYY-MM-DDTHH:MM:SS.000+0000",
        "stopTime": "YYYY-MM-DDTHH:MM:SS.000+0000",
        "voice": [
            {
                "mediaID": "",
                "startTime": "YYYY-MM-DDTHH:MM:SS.000+0000",
                "stopTime": "YYYY-MM-DDTHH:MM:SS.000+0000",
                "mediaPath": "",
                "encryption": "true",
                "duration": "2892000",
                "size": "5785352"
            }
        ],
        "screen": [
            {
                "mediaID": "",
                "startTime": "YYYY-MM-DDTHH:MM:SS.000+000",
                "stopTime": "YYYY-MM-DDTHH:MM:SS.000+000",
                "mediaPath": "",
                "encryption": "false",
                "duration": "2892000",
                "size": "5785352"
            }
        ]
    },
    {
        "case_id": "GIR_IRP_Muxer_Load_0_01",
        "startTime": "2016-04-25T20:00:00.000+0000",
        "stopTime": "2016-04-25T20:48:12.000+0000",
        "voice": [
            {
                "mediaID": "",
                "startTime": "2016-04-25T20:00:00.000+0000",
                "stopTime": "2016-04-25T20:48:12.000+0000",
                "mediaPath": "",
                "encryption": "true",
                "duration": "2892000",
                "size": "5785352"
            }
        ],
        "screen": [
            {
                "mediaID": "",
                "startTime": "2016-04-25T20:00:00.000+0000",
                "stopTime": "2016-04-25T21:04:06.000+0000",
                "mediaPath": "",
                "encryption": "true",
                "duration": "2892000",
                "size": "5785352"
            }
        ]
    },
    {
        "case_id": "GIR_IRP_Muxer_Load_0_02",
        "startTime": "2016-04-25T20:00:00.000+0000",
        "stopTime": "2016-04-25T20:16:01.000+0000",
        "voice": [
            {
                "mediaID": "072c871e-6c91-43cd-a8eb-f5f4e69e5317",
                "startTime": "2016-04-25T20:00:00.000+0000",
                "stopTime": "2016-04-25T20:16:04.000+0000",
                "mediaPath": "",
                "encryption": "true",
                "duration": "2892000",
                "size": "5785352"
            },
            {
                "mediaID": "b10c3f20-5357-4199-9769-1c0e3e41b4d0",
                "startTime": "2016-04-25T20:16:05.000+0000",
                "stopTime": "2016-04-25T20:32:08.000+0000",
                "mediaPath": "",
                "encryption": "true",
                "duration": "2892000",
                "size": "5785352"
            }
        ],
        "screen": [
            {
                "mediaID": "",
                "startTime": "2016-04-25T20:00:00.000+0000",
                "stopTime": "2016-04-25T20:16:01.000+0000",
                "mediaPath": "",
                "encryption": "true",
                "duration": "2892000",
                "size": "5785352"
            },
            {
                "mediaID": "",
                "startTime": "2016-04-25T20:16:01.000+0000",
                "stopTime": "2016-04-25T20:48:04.000+0000",
                "mediaPath": "",
                "encryption": "true",
                "duration": "2892000",
                "size": "5785352"
            }
        ]
    }
]